sudoku/core/__init__.py
sudoku/core/iterators.py
sudoku/core/sudoku_grid.py
sudoku/gui/AboutWindow.py
sudoku/gui/MainWindow.py
sudoku/gui/SudokuWidget.py
sudoku/gui/Ui_AboutWindow.py
sudoku/gui/Ui_MainWindow.py
sudoku/gui/__init__.py
sudoku/gui/__main__.py
bsum_sudoku-0.9.5.dist-info/LICENSE
bsum_sudoku-0.9.5.dist-info/METADATA
bsum_sudoku-0.9.5.dist-info/WHEEL
bsum_sudoku-0.9.5.dist-info/entry_points.txt
bsum_sudoku-0.9.5.dist-info/top_level.txt
bsum_sudoku-0.9.5.dist-info/zip-safe
bsum_sudoku-0.9.5.dist-info/RECORD
